Lab1/alu.vhd
library IEEE;
use IEEE.STD_LOGIC_1164.ALL;
use IEEE.NUMERIC_STD.ALL;

entity ALU is
    Port (
        A    : in  STD_LOGIC_VECTOR(15 downto 0);
        B    : in  STD_LOGIC_VECTOR(15 downto 0);
        OP   : in  STD_LOGIC_VECTOR(2 downto 0);
        CIN  : in  STD_LOGIC;
        R    : out STD_LOGIC_VECTOR(15 downto 0);
        COUT : out STD_LOGIC
    );
end ALU;

architecture Behavioral of ALU is
begin

    process(A, B, OP, CIN)
        variable tmp : unsigned(16 downto 0);
    begin

        R <= (others => '0');
        COUT <= '0';

        case OP is

            when "000" => -- AND
                R <= A and B;

            when "001" => -- XOR
                R <= A xor B;

            when "010" => -- ADD
                tmp := ('0' & unsigned(A)) + ('0' & unsigned(B));
                R <= std_logic_vector(tmp(15 downto 0));
                COUT <= tmp(16);

            when "011" => -- ADDC
                tmp := ('0' & unsigned(A)) +
                       ('0' & unsigned(B)) +
                       unsigned'(0 => CIN);
                R <= std_logic_vector(tmp(15 downto 0));
                COUT <= tmp(16);

            when "100" => -- SUB
                tmp := ('0' & unsigned(A)) - ('0' & unsigned(B));
                R <= std_logic_vector(tmp(15 downto 0));
                COUT <= tmp(16);

            when "101" => -- SRL
                R <= std_logic_vector(shift_right(unsigned(A), 1));
                COUT <= A(0);

            when "110" => -- SWAP
                R <= A(7 downto 0) & A(15 downto 8);

            when others =>
                R <= (others => '0');

        end case;

    end process;

end Behavioral;

Lab1/alur.vhd
library IEEE;
use IEEE.STD_LOGIC_1164.ALL;
use IEEE.NUMERIC_STD.ALL;

entity ALUR is
    Port (
        clk  : in  STD_LOGIC;                         -- Clock signal
        rst  : in  STD_LOGIC;                         -- Asynchronous reset
        A    : in  STD_LOGIC_VECTOR(15 downto 0);     -- Operand A
        B    : in  STD_LOGIC_VECTOR(15 downto 0);     -- Operand B
        OP   : in  STD_LOGIC_VECTOR(2 downto 0);      -- Operation code
        CIN  : in  STD_LOGIC;                         -- Carry input
        R    : out STD_LOGIC_VECTOR(15 downto 0);     -- Result output
        COUT : out STD_LOGIC                          -- Carry output
    );
end ALUR;

architecture Behavioral of ALUR is

    -- Registered inputs
    signal A_reg, B_reg : STD_LOGIC_VECTOR(15 downto 0);
    signal OP_reg       : STD_LOGIC_VECTOR(2 downto 0);
    signal CIN_reg      : STD_LOGIC;

    -- Combinational outputs from ALU
    signal R_comb  : STD_LOGIC_VECTOR(15 downto 0);
    signal C_comb  : STD_LOGIC;

begin

    -- Input registers
    process(clk, rst)
    begin
        if rst = '1' then
            A_reg <= (others => '0');
            B_reg <= (others => '0');
            OP_reg <= (others => '0');
            CIN_reg <= '0';
        elsif rising_edge(clk) then
            A_reg <= A;
            B_reg <= B;
            OP_reg <= OP;
            CIN_reg <= CIN;
        end if;
    end process;

    -- ALU instance (combinational block)
    ALU_inst: entity work.ALU
        port map(
            A => A_reg,
            B => B_reg,
            OP => OP_reg,
            CIN => CIN_reg,
            R => R_comb,
            COUT => C_comb
        );

    -- Output registers
    process(clk, rst)
    begin
        if rst = '1' then
            R <= (others => '0');
            COUT <= '0';
        elsif rising_edge(clk) then
            R <= R_comb;
            COUT <= C_comb;
        end if;
    end process;

end Behavioral;

Lab1/tb_alur.vhd
library IEEE;
use IEEE.STD_LOGIC_1164.ALL;
use IEEE.NUMERIC_STD.ALL;

entity tb_ALUR is
end tb_ALUR;

architecture Behavioral of tb_ALUR is

    signal clk  : STD_LOGIC := '0';
    signal rst  : STD_LOGIC := '1';
    signal A    : STD_LOGIC_VECTOR(15 downto 0);
    signal B    : STD_LOGIC_VECTOR(15 downto 0);
    signal OP   : STD_LOGIC_VECTOR(2 downto 0);
    signal CIN  : STD_LOGIC;
    signal R    : STD_LOGIC_VECTOR(15 downto 0);
    signal COUT : STD_LOGIC;

begin

    uut: entity work.ALUR
        port map(
            clk => clk,
            rst => rst,
            A => A,
            B => B,
            OP => OP,
            CIN => CIN,
            R => R,
            COUT => COUT
        );

    -- Clock generation (10 ns period)
    clk_process : process
    begin
        while now < 200 ns loop
            clk <= '0';
            wait for 5 ns;
            clk <= '1';
            wait for 5 ns;
        end loop;
        wait;
    end process;

    -- Stimulus process
    process
    begin
        wait for 20 ns;
        rst <= '0';

        A <= x"000A";
        B <= x"0005";
        CIN <= '1';

        OP <= "010"; -- ADD
        wait for 20 ns;
        report "ALUR ADD result = " &
               integer'image(to_integer(unsigned(R)));

        OP <= "011"; -- ADDC
        wait for 20 ns;
        report "ALUR ADDC result = " &
               integer'image(to_integer(unsigned(R)));

        OP <= "100"; -- SUB
        wait for 20 ns;
        report "ALUR SUB result = " &
               integer'image(to_integer(unsigned(R)));

        report "Simulation finished";
        wait;
    end process;

end Behavioral;

Lab1/alur.vcd
$date
  Fri Feb 20 12:22:03 2026
$end
$version
  GHDL v0
$end
$timescale
  1 fs
$end
$scope module standard $end
$upscope $end
$scope module std_logic_1164 $end
$upscope $end
$scope module numeric_std $end
$upscope $end
$scope module tb_alur $end
$var reg 1 ! clk $end
$var reg 1 " rst $end
$var reg 16 # a[15:0] $end
$var reg 16 $ b[15:0] $end
$var reg 3 % op[2:0] $end
$var reg 1 & cin $end
$var reg 16 ' r[15:0] $end
$var reg 1 ( cout $end
$scope module uut $end
$var reg 1 ) clk $end
$var reg 1 * rst $end
$var reg 16 + a[15:0] $end
$var reg 16 , b[15:0] $end
$var reg 3 - op[2:0] $end
$var reg 1 . cin $end
$var reg 16 / r[15:0] $end
$var reg 1 0 cout $end
$var reg 16 1 a_reg[15:0] $end
$var reg 16 2 b_reg[15:0] $end
$var reg 3 3 op_reg[2:0] $end
$var reg 1 4 cin_reg $end
$var reg 16 5 r_comb[15:0] $end
$var reg 1 6 c_comb $end
$scope module alu_inst $end
$var reg 16 7 a[15:0] $end
$var reg 16 8 b[15:0] $end
$var reg 3 9 op[2:0] $end
$var reg 1 : cin $end
$var reg 16 ; r[15:0] $end
$var reg 1 < cout $end
$upscope $end
$upscope $end
$upscope $end
$enddefinitions $end
#0
0!
1"
bUUUUUUUUUUUUUUUU #
bUUUUUUUUUUUUUUUU $
bUUU %
U&
b0000000000000000 '
0(
0)
1*
bUUUUUUUUUUUUUUUU +
bUUUUUUUUUUUUUUUU ,
bUUU -
U.
b0000000000000000 /
00
b0000000000000000 1
b0000000000000000 2
b000 3
04
b0000000000000000 5
06
b0000000000000000 7
b0000000000000000 8
b000 9
0:
b0000000000000000 ;
0<
#5000000
1!
1)
#10000000
0!
0)
#15000000
1!
1)
#20000000
0!
0"
b0000000000001010 #
b0000000000000101 $
b010 %
1&
0)
0*
b0000000000001010 +
b0000000000000101 ,
b010 -
1.
#25000000
1!
1)
b0000000000001010 1
b0000000000000101 2
b010 3
14
b0000000000001111 5
b0000000000001010 7
b0000000000000101 8
b010 9
1:
b0000000000001111 ;
#30000000
0!
0)
#35000000
1!
b0000000000001111 '
1)
b0000000000001111 /
#40000000
0!
b011 %
0)
b011 -
#45000000
1!
1)
b011 3
b0000000000010000 5
b011 9
b0000000000010000 ;
#50000000
0!
0)
#55000000
1!
b0000000000010000 '
1)
b0000000000010000 /
#60000000
0!
b100 %
0)
b100 -
#65000000
1!
1)
b100 3
b0000000000000101 5
b100 9
b0000000000000101 ;
#70000000
0!
0)
#75000000
1!
b0000000000000101 '
1)
b0000000000000101 /
