Lab2/fifo16.vhd
library IEEE;
use IEEE.STD_LOGIC_1164.ALL;
use IEEE.NUMERIC_STD.ALL;

entity fifo16 is
    Port (
        clk   : in  STD_LOGIC;
        rst   : in  STD_LOGIC;

        wr_en : in  STD_LOGIC;                         -- Write enable
        rd_en : in  STD_LOGIC;                         -- Read enable

        din   : in  STD_LOGIC_VECTOR(7 downto 0);      -- Data input
        dout  : out STD_LOGIC_VECTOR(7 downto 0);      -- Data output (show-ahead)

        full  : out STD_LOGIC;                         -- FIFO full flag
        empty : out STD_LOGIC                          -- FIFO empty flag
    );
end fifo16;

architecture rtl of fifo16 is

    type mem_t is array (0 to 15) of STD_LOGIC_VECTOR(7 downto 0);
    signal mem : mem_t;

    signal wr_ptr : unsigned(3 downto 0);
    signal rd_ptr : unsigned(3 downto 0);

    -- Count of stored elements: 0..16 (needs 5 bits)
    signal count : unsigned(4 downto 0);

begin

    -- Show-ahead output: always show current head element
    dout <= mem(to_integer(rd_ptr)) when count > 0 else (others => '0');

    -- Full/Empty flags
    full  <= '1' when count = 16 else '0';
    empty <= '1' when count = 0  else '0';

    process(clk, rst)
        variable do_write : boolean;
        variable do_read  : boolean;
    begin
        if rst = '1' then
            wr_ptr <= (others => '0');
            rd_ptr <= (others => '0');
            count  <= (others => '0');

        elsif rising_edge(clk) then
            do_write := (wr_en = '1') and (count < 16);
            do_read  := (rd_en = '1') and (count > 0);

            if do_write then
                mem(to_integer(wr_ptr)) <= din;
                wr_ptr <= wr_ptr + 1;
            end if;

            if do_read then
                rd_ptr <= rd_ptr + 1;
            end if;

            if do_write and (not do_read) then
                count <= count + 1;
            elsif do_read and (not do_write) then
                count <= count - 1;
            end if;
        end if;
    end process;

end rtl;

Lab2/detector.vhd
library IEEE;
use IEEE.STD_LOGIC_1164.ALL;
use IEEE.NUMERIC_STD.ALL;

entity detector is
    Port (
        clk        : in  STD_LOGIC;
        rst        : in  STD_LOGIC;

        -- Input stream
        start      : in  STD_LOGIC;                          -- Start detector
        ed         : in  STD_LOGIC;                          -- Input byte valid strobe
        di         : in  STD_LOGIC_VECTOR(7 downto 0);       -- ASCII byte input

        -- Outputs: detection flags (1-cycle pulses)
        flag_set   : out STD_LOGIC;
        flag_reset : out STD_LOGIC;
        flag_data  : out STD_LOGIC;

        -- Output data for 0Hcccc
        data_out   : out STD_LOGIC_VECTOR(15 downto 0);

        -- Optional debug/status
        ok         : out STD_LOGIC;
        err        : out STD_LOGIC
    );
end detector;

architecture rtl of detector is

    -- =========================
    -- FIFO interface signals
    -- =========================
    signal fifo_wr    : STD_LOGIC;
    signal fifo_rd    : STD_LOGIC;
    signal fifo_din   : STD_LOGIC_VECTOR(7 downto 0);
    signal fifo_dout  : STD_LOGIC_VECTOR(7 downto 0);
    signal fifo_full  : STD_LOGIC;
    signal fifo_empty : STD_LOGIC;

    -- Current symbol from FIFO (show-ahead)
    signal symb : STD_LOGIC_VECTOR(7 downto 0);

    -- =========================
    -- FSM states
    -- =========================
    type state_t is (
        IDLE,
        WAIT_FULL,
        ST_S,

        -- SET branch
        SET_S, SET_SE, SET_OK,

        -- RESET branch
        R_R, R_RE, R_RES, R_RESE, R_RESET_OK,

        -- 0Hcccc branch
        D_0, D_0H, D_H1, D_H2, D_H3, D_H4_OK,

        ERR_STATE
    );

    signal state, next_state : state_t;

    -- Hex accumulator for 0Hcccc (nibbles packed into 16-bit)
    signal hex_acc : STD_LOGIC_VECTOR(15 downto 0);

    -- 1-cycle pulses (registered)
    signal flag_set_r, flag_reset_r, flag_data_r : STD_LOGIC;

    -- Internal status
    signal err_r : STD_LOGIC;

    -- =========================
    -- Helpers: ASCII constants
    -- =========================
    constant C_NULL : STD_LOGIC_VECTOR(7 downto 0) := x"00";

    constant C_S : STD_LOGIC_VECTOR(7 downto 0) := x"53"; -- 'S'
    constant C_E : STD_LOGIC_VECTOR(7 downto 0) := x"45"; -- 'E'
    constant C_T : STD_LOGIC_VECTOR(7 downto 0) := x"54"; -- 'T'
    constant C_R : STD_LOGIC_VECTOR(7 downto 0) := x"52"; -- 'R'
    constant C_0 : STD_LOGIC_VECTOR(7 downto 0) := x"30"; -- '0'
    constant C_H : STD_LOGIC_VECTOR(7 downto 0) := x"48"; -- 'H'

    -- Return TRUE if symb is HEX [0-9A-F]
    function is_hex(sym : STD_LOGIC_VECTOR(7 downto 0)) return boolean is
        variable code : integer;
    begin
        code := to_integer(unsigned(sym));

        -- '0'..'9' => 16#30#..16#39#
        if (code >= 16#30#) and (code <= 16#39#) then
            return true;
        end if;

        -- 'A'..'F' => 16#41#..16#46#
        if (code >= 16#41#) and (code <= 16#46#) then
            return true;
        end if;

        return false;
    end function;

    -- Convert HEX ASCII [0-9A-F] to nibble (4-bit)
    function hex_to_nibble(sym : STD_LOGIC_VECTOR(7 downto 0)) return STD_LOGIC_VECTOR is
        variable code : integer;
        variable n    : unsigned(3 downto 0);
    begin
        code := to_integer(unsigned(sym));

        if (code >= 16#30#) and (code <= 16#39#) then
            -- '0'..'9'
            n := to_unsigned(code - 16#30#, 4);
        else
            -- 'A'..'F' -> 10..15
            n := to_unsigned(code - 16#41# + 10, 4);
        end if;

        return std_logic_vector(n);
    end function;

begin

    -- Outputs
    flag_set   <= flag_set_r;
    flag_reset <= flag_reset_r;
    flag_data  <= flag_data_r;

    ok  <= '1' when state /= IDLE else '0';
    err <= err_r;

    -- FIFO wiring
    fifo_din <= di;
    fifo_wr  <= ed;
    symb     <= fifo_dout;

    fifo16_inst: entity work.fifo16
        port map(
            clk   => clk,
            rst   => rst,
            wr_en => fifo_wr,
            rd_en => fifo_rd,
            din   => fifo_din,
            dout  => fifo_dout,
            full  => fifo_full,
            empty => fifo_empty
        );

    -- =========================
    -- FSM state register + outputs/registers updates
    -- =========================
    process(clk, rst)
        variable nib : STD_LOGIC_VECTOR(3 downto 0);
    begin
        if rst = '1' then
            state <= IDLE;

            flag_set_r   <= '0';
            flag_reset_r <= '0';
            flag_data_r  <= '0';

            data_out <= (others => '0');
            hex_acc  <= (others => '0');

            err_r <= '0';

        elsif rising_edge(clk) then
            state <= next_state;

            -- Flags are 1-cycle pulses
            flag_set_r   <= '0';
            flag_reset_r <= '0';
            flag_data_r  <= '0';

            -- Clear error by default (will be set when entering ERR_STATE)
            err_r <= '0';

            -- Clear accumulator at "0H" start
            if (state = D_0) and (next_state = D_0H) and (fifo_rd = '1') then
                hex_acc <= (others => '0');
            end if;

            -- Update hex accumulator when reading hex digits
            if fifo_rd = '1' and (state = D_0H or state = D_H1 or state = D_H2 or state = D_H3) then
                if is_hex(symb) then
                    nib := hex_to_nibble(symb);
                    case state is
                        when D_0H =>
                            hex_acc(15 downto 12) <= nib; -- 1st nibble
                        when D_H1 =>
                            hex_acc(11 downto 8)  <= nib; -- 2nd nibble
                        when D_H2 =>
                            hex_acc(7 downto 4)   <= nib; -- 3rd nibble
                        when D_H3 =>
                            hex_acc(3 downto 0)   <= nib; -- 4th nibble
                        when others =>
                            null;
                    end case;
                end if;
            end if;

            -- Latch outputs on successful terminator (NULL)
            if state = SET_OK and fifo_rd = '1' and symb = C_NULL then
                flag_set_r <= '1';
            end if;

            if state = R_RESET_OK and fifo_rd = '1' and symb = C_NULL then
                flag_reset_r <= '1';
            end if;

            if state = D_H4_OK and fifo_rd = '1' and symb = C_NULL then
                data_out <= hex_acc;
                flag_data_r <= '1';
            end if;

            -- Error flag when we enter ERR_STATE
            if next_state = ERR_STATE then
                err_r <= '1';
            end if;

        end if;
    end process;

    -- =========================
    -- FSM next-state logic + fifo_rd control
    -- =========================
    process(state, start, fifo_full, fifo_empty, symb)
        variable want_read : STD_LOGIC;
    begin
        next_state <= state;
        want_read  := '0';

        case state is

            when IDLE =>
                if start = '1' then
                    next_state <= WAIT_FULL;
                end if;

            when WAIT_FULL =>
                if fifo_full = '1' then
                    next_state <= ST_S;
                end if;

            when ST_S =>
                if fifo_empty = '0' then
                    want_read := '1';

                    if symb = C_NULL then
                        next_state <= ST_S;
                    elsif symb = C_S then
                        next_state <= SET_S;
                    elsif symb = C_R then
                        next_state <= R_R;
                    elsif symb = C_0 then
                        next_state <= D_0;
                    else
                        next_state <= ERR_STATE;
                    end if;
                end if;

            -- ===== SET =====
            when SET_S =>
                if fifo_empty = '0' then
                    want_read := '1';
                    if symb = C_E then
                        next_state <= SET_SE;
                    elsif symb = C_NULL then
                        next_state <= ST_S;
                    else
                        next_state <= ERR_STATE;
                    end if;
                end if;

            when SET_SE =>
                if fifo_empty = '0' then
                    want_read := '1';
                    if symb = C_T then
                        next_state <= SET_OK;
                    elsif symb = C_NULL then
                        next_state <= ST_S;
                    else
                        next_state <= ERR_STATE;
                    end if;
                end if;

            when SET_OK =>
                if fifo_empty = '0' then
                    want_read := '1';
                    if symb = C_NULL then
                        next_state <= ST_S;
                    else
                        next_state <= ERR_STATE;
                    end if;
                end if;

            -- ===== RESET =====
            when R_R =>
                if fifo_empty = '0' then
                    want_read := '1';
                    if symb = C_E then
                        next_state <= R_RE;
                    elsif symb = C_NULL then
                        next_state <= ST_S;
                    else
                        next_state <= ERR_STATE;
                    end if;
                end if;

            when R_RE =>
                if fifo_empty = '0' then
                    want_read := '1';
                    if symb = C_S then
                        next_state <= R_RES;
                    elsif symb = C_NULL then
                        next_state <= ST_S;
                    else
                        next_state <= ERR_STATE;
                    end if;
                end if;

            when R_RES =>
                if fifo_empty = '0' then
                    want_read := '1';
                    if symb = C_E then
                        next_state <= R_RESE;
                    elsif symb = C_NULL then
                        next_state <= ST_S;
                    else
                        next_state <= ERR_STATE;
                    end if;
                end if;

            when R_RESE =>
                if fifo_empty = '0' then
                    want_read := '1';
                    if symb = C_T then
                        next_state <= R_RESET_OK;
                    elsif symb = C_NULL then
                        next_state <= ST_S;
                    else
                        next_state <= ERR_STATE;
                    end if;
                end if;

            when R_RESET_OK =>
                if fifo_empty = '0' then
                    want_read := '1';
                    if symb = C_NULL then
                        next_state <= ST_S;
                    else
                        next_state <= ERR_STATE;
                    end if;
                end if;

            -- ===== 0Hcccc =====
            when D_0 =>
                if fifo_empty = '0' then
                    want_read := '1';
                    if symb = C_H then
                        next_state <= D_0H;
                    elsif symb = C_NULL then
                        next_state <= ST_S;
                    else
                        next_state <= ERR_STATE;
                    end if;
                end if;

            when D_0H =>
                if fifo_empty = '0' then
                    want_read := '1';
                    if is_hex(symb) then
                        next_state <= D_H1;
                    else
                        next_state <= ERR_STATE;
                    end if;
                end if;

            when D_H1 =>
                if fifo_empty = '0' then
                    want_read := '1';
                    if is_hex(symb) then
                        next_state <= D_H2;
                    else
                        next_state <= ERR_STATE;
                    end if;
                end if;

            when D_H2 =>
                if fifo_empty = '0' then
                    want_read := '1';
                    if is_hex(symb) then
                        next_state <= D_H3;
                    else
                        next_state <= ERR_STATE;
                    end if;
                end if;

            when D_H3 =>
                if fifo_empty = '0' then
                    want_read := '1';
                    if is_hex(symb) then
                        next_state <= D_H4_OK;
                    else
                        next_state <= ERR_STATE;
                    end if;
                end if;

            when D_H4_OK =>
                if fifo_empty = '0' then
                    want_read := '1';
                    if symb = C_NULL then
                        next_state <= ST_S;
                    else
                        next_state <= ERR_STATE;
                    end if;
                end if;

            -- ===== ERROR =====
            when ERR_STATE =>
                if fifo_empty = '0' then
                    want_read := '1';
                    if symb = C_NULL then
                        next_state <= ST_S;
                    else
                        next_state <= ERR_STATE;
                    end if;
                end if;

        end case;

        fifo_rd <= want_read;
    end process;

end rtl;

Lab2/tb_detector.vhd
library IEEE;
use IEEE.STD_LOGIC_1164.ALL;
use IEEE.NUMERIC_STD.ALL;

entity tb_detector is
end tb_detector;

architecture sim of tb_detector is

    -- DUT signals
    signal clk        : STD_LOGIC := '0';
    signal rst        : STD_LOGIC := '1';

    signal start      : STD_LOGIC := '0';
    signal ed         : STD_LOGIC := '0';
    signal di         : STD_LOGIC_VECTOR(7 downto 0) := (others => '0');

    signal flag_set   : STD_LOGIC;
    signal flag_reset : STD_LOGIC;
    signal flag_data  : STD_LOGIC;
    signal data_out   : STD_LOGIC_VECTOR(15 downto 0);
    signal ok         : STD_LOGIC;
    signal err        : STD_LOGIC;

    -- ASCII constants
    constant C_NULL : STD_LOGIC_VECTOR(7 downto 0) := x"00";
    constant C_S    : STD_LOGIC_VECTOR(7 downto 0) := x"53"; -- 'S'
    constant C_E    : STD_LOGIC_VECTOR(7 downto 0) := x"45"; -- 'E'
    constant C_T    : STD_LOGIC_VECTOR(7 downto 0) := x"54"; -- 'T'
    constant C_R    : STD_LOGIC_VECTOR(7 downto 0) := x"52"; -- 'R'
    constant C_0    : STD_LOGIC_VECTOR(7 downto 0) := x"30"; -- '0'
    constant C_H    : STD_LOGIC_VECTOR(7 downto 0) := x"48"; -- 'H'
    constant C_A    : STD_LOGIC_VECTOR(7 downto 0) := x"41"; -- 'A'
    constant C_1    : STD_LOGIC_VECTOR(7 downto 0) := x"31"; -- '1'
    constant C_2    : STD_LOGIC_VECTOR(7 downto 0) := x"32"; -- '2'
    constant C_F    : STD_LOGIC_VECTOR(7 downto 0) := x"46"; -- 'F'

    -- Convert 4-bit nibble to ASCII hex char
    function nibble_to_char(n : STD_LOGIC_VECTOR(3 downto 0)) return character is
        variable v : integer;
    begin
        v := to_integer(unsigned(n));
        if v < 10 then
            return character'val(character'pos('0') + v);
        else
            return character'val(character'pos('A') + (v - 10));
        end if;
    end function;

    -- Convert 16-bit vector to 4-char hex string
    function to_hex4(x : STD_LOGIC_VECTOR(15 downto 0)) return string is
        variable s : string(1 to 4);
    begin
        s(1) := nibble_to_char(x(15 downto 12));
        s(2) := nibble_to_char(x(11 downto 8));
        s(3) := nibble_to_char(x(7 downto 4));
        s(4) := nibble_to_char(x(3 downto 0));
        return s;
    end function;

    -- Push a byte into DUT input stream (ED strobe for 1 clock)
    procedure push_byte(
        signal di_s  : out STD_LOGIC_VECTOR(7 downto 0);
        signal ed_s  : out STD_LOGIC;
        signal clk_s : in  STD_LOGIC;
        b            : in  STD_LOGIC_VECTOR(7 downto 0)
    ) is
    begin
        di_s <= b;
        ed_s <= '1';
        wait until rising_edge(clk_s);
        ed_s <= '0';
        wait until rising_edge(clk_s);
    end procedure;

begin

    -- Instantiate DUT
    uut: entity work.detector
        port map(
            clk        => clk,
            rst        => rst,
            start      => start,
            ed         => ed,
            di         => di,
            flag_set   => flag_set,
            flag_reset => flag_reset,
            flag_data  => flag_data,
            data_out   => data_out,
            ok         => ok,
            err        => err
        );

    -- Clock generation: 10 ns period
    clk_gen : process
    begin
        while now < 2000 ns loop
            clk <= '0';
            wait for 5 ns;
            clk <= '1';
            wait for 5 ns;
        end loop;
        wait;
    end process;

    -- Monitor: print detections
    monitor : process(clk)
        variable data_int : integer;
    begin
        if rising_edge(clk) then
            if flag_data = '1' then
                data_int := to_integer(unsigned(data_out));
                report "DETECTED: DATA 0x" & to_hex4(data_out) &
                       " (" & integer'image(data_int) & ")" severity note;
            end if;

            if flag_set = '1' then
                report "DETECTED: SET" severity note;
            end if;

            if flag_reset = '1' then
                report "DETECTED: RESET" severity note;
            end if;

            if err = '1' then
                report "ERROR STATE ACTIVE" severity note;
            end if;
        end if;
    end process;

    -- Stimulus
    stim : process
    begin
        -- Reset
        wait for 20 ns;
        rst <= '0';
        wait until rising_edge(clk);

        -- Start detector
        start <= '1';
        wait until rising_edge(clk);
        start <= '0';

        -- ==========================================================
        -- IMPORTANT:
        -- Detector starts processing only when FIFO becomes FULL (16).
        -- We MUST ensure that the DATA word (0Hcccc + NULL) is already
        -- inside FIFO before it becomes FULL.
        --
        -- First 16 bytes we push:
        --  0H1A2F\0  -> 7 bytes
        --  SET\0     -> 4 bytes (total 11)
        --  NULL x5   -> 5 bytes (total 16) => FIFO becomes FULL here
        -- ==========================================================

        -- 0H1A2F\0  (7 bytes)
        push_byte(di, ed, clk, C_0);
        push_byte(di, ed, clk, C_H);
        push_byte(di, ed, clk, C_1);
        push_byte(di, ed, clk, C_A);
        push_byte(di, ed, clk, C_2);
        push_byte(di, ed, clk, C_F);
        push_byte(di, ed, clk, C_NULL);

        -- SET\0 (4 bytes) -> total 11
        push_byte(di, ed, clk, C_S);
        push_byte(di, ed, clk, C_E);
        push_byte(di, ed, clk, C_T);
        push_byte(di, ed, clk, C_NULL);

        -- Pad with NULLs to reach exactly 16 bytes -> add 5 NULLs
        push_byte(di, ed, clk, C_NULL);
        push_byte(di, ed, clk, C_NULL);
        push_byte(di, ed, clk, C_NULL);
        push_byte(di, ed, clk, C_NULL);
        push_byte(di, ed, clk, C_NULL);

        -- After processing starts, push RESET\0 as additional stream
        wait for 80 ns;
        push_byte(di, ed, clk, C_R);
        push_byte(di, ed, clk, C_E);
        push_byte(di, ed, clk, C_S);
        push_byte(di, ed, clk, C_E);
        push_byte(di, ed, clk, C_T);
        push_byte(di, ed, clk, C_NULL);

        -- Add noise: XY\0 (should go ERR until NULL)
        wait for 50 ns;
        push_byte(di, ed, clk, x"58"); -- 'X'
        push_byte(di, ed, clk, x"59"); -- 'Y'
        push_byte(di, ed, clk, C_NULL);

        -- Finish
        wait for 200 ns;
        report "TB finished" severity note;
        wait;
    end process;

end sim;

Lab2/detector.vcd
$date
  Fri Feb 20 13:39:40 2026
$end
$version
  GHDL v0
$end
$timescale
  1 fs
$end
$scope module standard $end
$upscope $end
$scope module std_logic_1164 $end
$upscope $end
$scope module numeric_std $end
$upscope $end
$scope module tb_detector $end
$var reg 1 ! clk $end
$var reg 1 " rst $end
$var reg 1 # start $end
$var reg 1 $ ed $end
$var reg 8 % di[7:0] $end
$var reg 1 & flag_set $end
$var reg 1 ' flag_reset $end
$var reg 1 ( flag_data $end
$var reg 16 ) data_out[15:0] $end
$var reg 1 * ok $end
$var reg 1 + err $end
$scope module uut $end
$var reg 1 , clk $end
$var reg 1 - rst $end
$var reg 1 . start $end
$var reg 1 / ed $end
$var reg 8 0 di[7:0] $end
$var reg 1 1 flag_set $end
$var reg 1 2 flag_reset $end
$var reg 1 3 flag_data $end
$var reg 16 4 data_out[15:0] $end
$var reg 1 5 ok $end
$var reg 1 6 err $end
$var reg 1 7 fifo_wr $end
$var reg 1 8 fifo_rd $end
$var reg 8 9 fifo_din[7:0] $end
$var reg 8 : fifo_dout[7:0] $end
$var reg 1 ; fifo_full $end
$var reg 1 < fifo_empty $end
$var reg 8 = symb[7:0] $end
$comment state is not handled $end
$comment next_state is not handled $end
$var reg 16 > hex_acc[15:0] $end
$var reg 1 ? flag_set_r $end
$var reg 1 @ flag_reset_r $end
$var reg 1 A flag_data_r $end
$var reg 1 B err_r $end
$scope module fifo16_inst $end
$var reg 1 C clk $end
$var reg 1 D rst $end
$var reg 1 E wr_en $end
$var reg 1 F rd_en $end
$var reg 8 G din[7:0] $end
$var reg 8 H dout[7:0] $end
$var reg 1 I full $end
$var reg 1 J empty $end
$comment mem is not handled $end
$var reg 4 K wr_ptr[3:0] $end
$var reg 4 L rd_ptr[3:0] $end
$var reg 5 M count[4:0] $end
$upscope $end
$upscope $end
$upscope $end
$enddefinitions $end
#0
0!
1"
0#
0$
b00000000 %
0&
0'
0(
b0000000000000000 )
0*
0+
0,
1-
0.
0/
b00000000 0
01
02
03
b0000000000000000 4
05
06
07
08
b00000000 9
b00000000 :
0;
1<
b00000000 =
b0000000000000000 >
0?
0@
0A
0B
0C
1D
0E
0F
b00000000 G
b00000000 H
0I
1J
b0000 K
b0000 L
b00000 M
#5000000
1!
1,
1C
#10000000
0!
0,
0C
#15000000
1!
1,
1C
#20000000
0!
0"
0,
0-
0C
0D
#25000000
1!
1#
1,
1.
1C
#30000000
0!
0,
0C
#35000000
1!
0#
1$
b00110000 %
1*
1,
0.
1/
b00110000 0
15
17
b00110000 9
1C
1E
b00110000 G
#40000000
0!
0,
0C
#45000000
1!
0$
1,
0/
07
b00110000 :
0<
b00110000 =
1C
0E
b00110000 H
0J
b0001 K
b00001 M
#50000000
0!
0,
0C
#55000000
1!
1$
b01001000 %
1,
1/
b01001000 0
17
b01001000 9
1C
1E
b01001000 G
#60000000
0!
0,
0C
#65000000
1!
0$
1,
0/
07
1C
0E
b0010 K
b00010 M
#70000000
0!
0,
0C
#75000000
1!
1$
b00110001 %
1,
1/
b00110001 0
17
b00110001 9
1C
1E
b00110001 G
#80000000
0!
0,
0C
#85000000
1!
0$
1,
0/
07
1C
0E
b0011 K
b00011 M
#90000000
0!
0,
0C
#95000000
1!
1$
b01000001 %
1,
1/
b01000001 0
17
b01000001 9
1C
1E
b01000001 G
#100000000
0!
0,
0C
#105000000
1!
0$
1,
0/
07
1C
0E
b0100 K
b00100 M
#110000000
0!
0,
0C
#115000000
1!
1$
b00110010 %
1,
1/
b00110010 0
17
b00110010 9
1C
1E
b00110010 G
#120000000
0!
0,
0C
#125000000
1!
0$
1,
0/
07
1C
0E
b0101 K
b00101 M
#130000000
0!
0,
0C
#135000000
1!
1$
b01000110 %
1,
1/
b01000110 0
17
b01000110 9
1C
1E
b01000110 G
#140000000
0!
0,
0C
#145000000
1!
0$
1,
0/
07
1C
0E
b0110 K
b00110 M
#150000000
0!
0,
0C
#155000000
1!
1$
b00000000 %
1,
1/
b00000000 0
17
b00000000 9
1C
1E
b00000000 G
#160000000
0!
0,
0C
#165000000
1!
0$
1,
0/
07
1C
0E
b0111 K
b00111 M
#170000000
0!
0,
0C
#175000000
1!
1$
b01010011 %
1,
1/
b01010011 0
17
b01010011 9
1C
1E
b01010011 G
#180000000
0!
0,
0C
#185000000
1!
0$
1,
0/
07
1C
0E
b1000 K
b01000 M
#190000000
0!
0,
0C
#195000000
1!
1$
b01000101 %
1,
1/
b01000101 0
17
b01000101 9
1C
1E
b01000101 G
#200000000
0!
0,
0C
#205000000
1!
0$
1,
0/
07
1C
0E
b1001 K
b01001 M
#210000000
0!
0,
0C
#215000000
1!
1$
b01010100 %
1,
1/
b01010100 0
17
b01010100 9
1C
1E
b01010100 G
#220000000
0!
0,
0C
#225000000
1!
0$
1,
0/
07
1C
0E
b1010 K
b01010 M
#230000000
0!
0,
0C
#235000000
1!
1$
b00000000 %
1,
1/
b00000000 0
17
b00000000 9
1C
1E
b00000000 G
#240000000
0!
0,
0C
#245000000
1!
0$
1,
0/
07
1C
0E
b1011 K
b01011 M
#250000000
0!
0,
0C
#255000000
1!
1$
1,
1/
17
1C
1E
#260000000
0!
0,
0C
#265000000
1!
0$
1,
0/
07
1C
0E
b1100 K
b01100 M
#270000000
0!
0,
0C
#275000000
1!
1$
1,
1/
17
1C
1E
#280000000
0!
0,
0C
#285000000
1!
0$
1,
0/
07
1C
0E
b1101 K
b01101 M
#290000000
0!
0,
0C
#295000000
1!
1$
1,
1/
17
1C
1E
#300000000
0!
0,
0C
#305000000
1!
0$
1,
0/
07
1C
0E
b1110 K
b01110 M
#310000000
0!
0,
0C
#315000000
1!
1$
1,
1/
17
1C
1E
#320000000
0!
0,
0C
#325000000
1!
0$
1,
0/
07
1C
0E
b1111 K
b01111 M
#330000000
0!
0,
0C
#335000000
1!
1$
1,
1/
17
1C
1E
#340000000
0!
0,
0C
#345000000
1!
0$
1,
0/
07
1;
1C
0E
1I
b0000 K
b10000 M
#350000000
0!
0,
0C
#355000000
1!
1,
18
1C
1F
#360000000
0!
0,
0C
#365000000
1!
1,
b01001000 :
0;
b01001000 =
1C
b01001000 H
0I
b0001 L
b01111 M
#370000000
0!
0,
0C
#375000000
1!
1,
b00110001 :
b00110001 =
1C
b00110001 H
b0010 L
b01110 M
#380000000
0!
0,
0C
#385000000
1!
1,
b01000001 :
b01000001 =
b0001000000000000 >
1C
b01000001 H
b0011 L
b01101 M
#390000000
0!
0,
0C
#395000000
1!
1,
b00110010 :
b00110010 =
b0001101000000000 >
1C
b00110010 H
b0100 L
b01100 M
#400000000
0!
0,
0C
#405000000
1!
1,
b01000110 :
b01000110 =
b0001101000100000 >
1C
b01000110 H
b0101 L
b01011 M
#410000000
0!
0,
0C
#415000000
1!
1,
b00000000 :
b00000000 =
b0001101000101111 >
1C
b00000000 H
b0110 L
b01010 M
#420000000
0!
0,
0C
#425000000
1!
1(
b0001101000101111 )
1,
13
b0001101000101111 4
b01010011 :
b01010011 =
1A
1C
b01010011 H
b0111 L
b01001 M
#430000000
0!
0,
0C
#435000000
1!
0$
b01010010 %
0(
1,
0/
b01010010 0
03
07
b01010010 9
b01000101 :
b01000101 =
0A
1C
0E
b01010010 G
b01000101 H
b1000 L
b01000 M
#440000000
0!
0,
0C
#445000000
1!
1$
b01000101 %
1,
1/
b01000101 0
17
b01000101 9
b01010100 :
b01010100 =
1C
1E
b01000101 G
b01010100 H
b1001 L
b00111 M
#450000000
0!
0,
0C
#455000000
1!
0$
1,
0/
07
b00000000 :
b00000000 =
1C
0E
b00000000 H
b0001 K
b1010 L
#460000000
0!
0,
0C
#465000000
1!
1$
b01010011 %
1&
1,
1/
b01010011 0
11
17
b01010011 9
1?
1C
1E
b01010011 G
b1011 L
b00110 M
#470000000
0!
0,
0C
#475000000
1!
0$
0&
1,
0/
01
07
0?
1C
0E
b0010 K
b1100 L
#480000000
0!
0,
0C
#485000000
1!
1$
b01000101 %
1,
1/
b01000101 0
17
b01000101 9
1C
1E
b01000101 G
b1101 L
b00101 M
#490000000
0!
0,
0C
#495000000
1!
0$
1,
0/
07
1C
0E
b0011 K
b1110 L
#500000000
0!
0,
0C
#505000000
1!
1$
b01010100 %
1,
1/
b01010100 0
17
b01010100 9
1C
1E
b01010100 G
b1111 L
b00100 M
#510000000
0!
0,
0C
#515000000
1!
0$
1,
0/
07
b01000101 :
b01000101 =
1C
0E
b01000101 H
b0100 K
b0000 L
#520000000
0!
0,
0C
#525000000
1!
1$
b00000000 %
1+
1,
1/
b00000000 0
16
17
b00000000 9
b01010011 :
b01010011 =
1B
1C
1E
b00000000 G
b01010011 H
b0001 L
b00011 M
#530000000
0!
0,
0C
#535000000
1!
0$
1,
0/
07
b01000101 :
b01000101 =
1C
0E
b01000101 H
b0101 K
b0010 L
#540000000
0!
0,
0C
#545000000
1!
1,
b01010100 :
b01010100 =
1C
b01010100 H
b0011 L
b00010 M
#550000000
0!
0,
0C
#555000000
1!
1,
b00000000 :
b00000000 =
1C
b00000000 H
b0100 L
b00001 M
#560000000
0!
0,
0C
#565000000
1!
0+
1,
06
08
1<
0B
1C
0F
1J
b0101 L
b00000 M
#570000000
0!
0,
0C
#575000000
1!
1,
1C
#580000000
0!
0,
0C
#585000000
1!
1,
1C
#590000000
0!
0,
0C
#595000000
1!
0$
b01011000 %
1,
0/
b01011000 0
07
b01011000 9
1C
0E
b01011000 G
#600000000
0!
0,
0C
#605000000
1!
1$
b01011001 %
1,
1/
b01011001 0
17
b01011001 9
1C
1E
b01011001 G
#610000000
0!
0,
0C
#615000000
1!
0$
1,
0/
07
18
b01011001 :
0<
b01011001 =
1C
0E
1F
b01011001 H
0J
b0110 K
b00001 M
#620000000
0!
0,
0C
#625000000
1!
1$
b00000000 %
1+
1,
1/
b00000000 0
16
17
08
b00000000 9
b00000000 :
1<
b00000000 =
1B
1C
1E
0F
b00000000 G
b00000000 H
1J
b0110 L
b00000 M
#630000000
0!
0,
0C
#635000000
1!
0$
1,
0/
07
18
0<
1C
0E
1F
0J
b0111 K
b00001 M
#640000000
0!
0,
0C
#645000000
1!
0+
1,
06
08
1<
0B
1C
0F
1J
b0111 L
b00000 M
